PercentageOfCorrectKeyPointsByAmir/PercentageOfCorrectKeyPoints.py
PercentageOfCorrectKeyPointsByAmir/__init__.py
percentageofcorrectkeypointsbyamir-0.1.2.dist-info/METADATA
percentageofcorrectkeypointsbyamir-0.1.2.dist-info/WHEEL
percentageofcorrectkeypointsbyamir-0.1.2.dist-info/top_level.txt
percentageofcorrectkeypointsbyamir-0.1.2.dist-info/RECORD
