Metadata-Version: 2.4
Name: PercentageOfCorrectKeyPointsByAmir
Version: 0.1.2
Summary: A sample package taht calcualtes Percentage Of CorrectKey Points
Home-page: https://github.com/yourusername/my_package
Author: Amir Dalili
Classifier: Programming Language :: Python :: 3
Requires-Python: >=3.6
Dynamic: author
Dynamic: classifier
Dynamic: home-page
Dynamic: requires-python
Dynamic: summary
